NBTExplorer/__init__.py
nbtexplorer-2.0.dist-info/licenses/LICENSE
nbtexplorer-2.0.dist-info/METADATA
nbtexplorer-2.0.dist-info/WHEEL
nbtexplorer-2.0.dist-info/top_level.txt
nbtexplorer-2.0.dist-info/RECORD
